ecco/__init__.py
ecco/__main__.py
ecco/activations.py
ecco/analysis.py
ecco/attribution.py
ecco/cli.py
ecco/lm.py
ecco/lm.py.orig
ecco/lm_plots.py
ecco/model-config.yaml
ecco/output.py
ecco/util.py
ecco/html/Ecco-Attention.html
ecco/html/NeuronViz.html
ecco/html/basic.html
ecco/html/cluster_explorable.html
ecco/html/gradient_explorable.html
ecco/html/heatmap_single.html
ecco/html/layer_activations.html
ecco/html/neuron_explorable.html
ecco/html/output_sequence.html
ecco/html/pca_explorable.html
ecco/html/predict_token.html
ecco/html/setup.html
ecco/html/styles.css
ecco/html/trace_tokens.html
ecco/svcca_lib/CHANGES
ecco/svcca_lib/LICENSE
ecco/svcca_lib/cca_core.py
ecco/svcca_lib/cka_lib.py
ecco/svcca_lib/pwcca.py
ecco-0.1.2.dist-info/AUTHORS.rst
ecco-0.1.2.dist-info/LICENSE
ecco-0.1.2.dist-info/METADATA
ecco-0.1.2.dist-info/WHEEL
ecco-0.1.2.dist-info/dependency_links.txt
ecco-0.1.2.dist-info/entry_points.txt
ecco-0.1.2.dist-info/top_level.txt
ecco-0.1.2.dist-info/RECORD
