Metadata-Version: 2.1
Name: ecco
Version: 0.1.2
Summary: Visualization tools for NLP machine learning models.
Home-page: https://github.com/jalammar/ecco
Author: Jay Alammar
Author-email: alammar@gmail.com
License: BSD-3-Clause
Project-URL: Changelog, https://github.com/jalammar/ecco/blob/master/CHANGELOG.rst
Project-URL: Issue Tracker, https://github.com/jalammar/ecco/issues
Keywords: Natural Language Processing,Explainable AI,keyword3
Platform: UNKNOWN
Classifier: Development Status :: 5 - Production/Stable
Classifier: Intended Audience :: Developers
Classifier: License :: OSI Approved :: BSD License
Classifier: Operating System :: Unix
Classifier: Operating System :: POSIX
Classifier: Operating System :: Microsoft :: Windows
Classifier: Programming Language :: Python
Classifier: Programming Language :: Python :: 3.7
Classifier: Programming Language :: Python :: 3.8
Classifier: Programming Language :: Python :: 3.9
Classifier: Programming Language :: Python :: Implementation :: CPython
Classifier: Programming Language :: Python :: Implementation :: PyPy
Classifier: Topic :: Utilities
Requires-Python: !=3.0.*, !=3.1.*, !=3.2.*, !=3.3.*, !=3.4.*
Requires-Dist: transformers (~=4.2)
Requires-Dist: seaborn (~=0.11)
Requires-Dist: scikit-learn (~=0.23)
Requires-Dist: PyYAML (~=5.4)
Requires-Dist: captum (~=0.4)
Provides-Extra: dev
Requires-Dist: pytest (>=6.1) ; extra == 'dev'
